LICENSE
README.md
setup.py
rpa_coop/__init__.py
rpa_coop/rpa_coop.py
rpa_coop/img/hash
rpa_coop/img/relatorios_azul.PNG
rpa_coop/img/relatorios_verde.PNG
rpa_coop/img/sacg_branco.PNG
rpa_coop/img/sagc_verde.PNG
rpa_coop/img/siac_amarelo.PNG
rpa_coop/img/siac_branco.PNG
rpa_coop/img/siat_amarelo.PNG
rpa_coop/img/siat_branco.PNG
rpa_coop/img/testes.py
rpa_coop/img/transacional_azul.PNG
rpa_coop/img/transacional_verde.PNG
rpa_cooperativa.egg-info/PKG-INFO
rpa_cooperativa.egg-info/SOURCES.txt
rpa_cooperativa.egg-info/dependency_links.txt
rpa_cooperativa.egg-info/not-zip-safe
rpa_cooperativa.egg-info/requires.txt
rpa_cooperativa.egg-info/top_level.txt