Metadata-Version: 2.1
Name: rpa-cooperativa
Version: 1.0.90
Summary: Classes referente automação com python para... api fluid, api whatsapp, api sms, sql, acc
Home-page: https://github.com/edenilsonsantos/rpa_cooperativa
Author: Edenilson Fernandes dos Santos
Author-email: santoeen@gmail.com
License: MIT License
Project-URL: repository, https://github.com/edenilsonsantos/rpa_cooperativa
Keywords: rpa cooperativa fluid api automação sql sqlalchemy
Classifier: Development Status :: 5 - Production/Stable
Classifier: Programming Language :: Python :: 3
Classifier: Programming Language :: Python :: 3.9
Classifier: Programming Language :: Python :: 3.10
Classifier: Programming Language :: Python :: 3.11
Classifier: License :: OSI Approved :: MIT License
Classifier: Intended Audience :: Developers
Classifier: Operating System :: POSIX :: Linux
Classifier: Operating System :: MacOS :: MacOS X
Classifier: Operating System :: Microsoft :: Windows
Classifier: Topic :: Software Development :: Libraries :: Python Modules
Requires-Python: >=3.8
License-File: LICENSE
